NCBImeta-0.8.3.data/scripts/NCBImeta
NCBImeta-0.8.3.data/scripts/NCBImetaAnnotate
NCBImeta-0.8.3.data/scripts/NCBImetaExport
NCBImeta-0.8.3.data/scripts/NCBImetaJoin
ncbimeta/NCBImetaErrors.py
ncbimeta/NCBImetaUtilities.py
ncbimeta/__init__.py
NCBImeta-0.8.3.dist-info/LICENSE
NCBImeta-0.8.3.dist-info/METADATA
NCBImeta-0.8.3.dist-info/WHEEL
NCBImeta-0.8.3.dist-info/top_level.txt
NCBImeta-0.8.3.dist-info/RECORD
