Metadata-Version: 2.1
Name: NCBImeta
Version: 0.8.3
Summary: Efficient and comprehensive metadata acquisition from the NCBI databases (includes SRA).
Home-page: https://ktmeaton.github.io/NCBImeta/
Author: Katherine Eaton
Author-email: ktmeaton@gmail.com
License: MIT
Platform: UNKNOWN
Classifier: Programming Language :: Python :: 3
Classifier: License :: OSI Approved :: MIT License
Requires-Python: >=3.7,<3.10
License-File: LICENSE
Requires-Dist: biopython (>=1.74)
Requires-Dist: lxml (>=4.6.3)
Requires-Dist: PyYAML (>=5.4)
Requires-Dist: numpy
Provides-Extra: dev
Requires-Dist: coverage ; extra == 'dev'
Requires-Dist: codecov ; extra == 'dev'
Requires-Dist: pytest ; extra == 'dev'
Requires-Dist: pytest-cov ; extra == 'dev'
Requires-Dist: check-manifest ; extra == 'dev'
Requires-Dist: twine ; extra == 'dev'
Requires-Dist: pre-commit ; extra == 'dev'
Requires-Dist: flake8 ; extra == 'dev'
Requires-Dist: flake8-bugbear ; extra == 'dev'
Requires-Dist: black ; extra == 'dev'
